monaco_2018_report/__init__.py
monaco_2018_report/report.py
monaco_2018_report/venv/Lib/site-packages/_virtualenv.py
monaco_2018_report/venv/Lib/site-packages/_distutils_hack/__init__.py
monaco_2018_report/venv/Lib/site-packages/_distutils_hack/override.py
monaco_2018_report/venv/Lib/site-packages/build/__init__.py
monaco_2018_report/venv/Lib/site-packages/build/__main__.py
monaco_2018_report/venv/Lib/site-packages/build/_builder.py
monaco_2018_report/venv/Lib/site-packages/build/_ctx.py
monaco_2018_report/venv/Lib/site-packages/build/_exceptions.py
monaco_2018_report/venv/Lib/site-packages/build/_types.py
monaco_2018_report/venv/Lib/site-packages/build/_util.py
monaco_2018_report/venv/Lib/site-packages/build/env.py
monaco_2018_report/venv/Lib/site-packages/build/py.typed
monaco_2018_report/venv/Lib/site-packages/build/util.py
monaco_2018_report/venv/Lib/site-packages/build/_compat/__init__.py
monaco_2018_report/venv/Lib/site-packages/build/_compat/importlib.py
monaco_2018_report/venv/Lib/site-packages/build/_compat/tarfile.py
monaco_2018_report/venv/Lib/site-packages/build/_compat/tomllib.py
monaco_2018_report/venv/Lib/site-packages/colorama/__init__.py
monaco_2018_report/venv/Lib/site-packages/colorama/ansi.py
monaco_2018_report/venv/Lib/site-packages/colorama/ansitowin32.py
monaco_2018_report/venv/Lib/site-packages/colorama/initialise.py
monaco_2018_report/venv/Lib/site-packages/colorama/win32.py
monaco_2018_report/venv/Lib/site-packages/colorama/winterm.py
monaco_2018_report/venv/Lib/site-packages/colorama/tests/__init__.py
monaco_2018_report/venv/Lib/site-packages/colorama/tests/ansi_test.py
monaco_2018_report/venv/Lib/site-packages/colorama/tests/ansitowin32_test.py
monaco_2018_report/venv/Lib/site-packages/colorama/tests/initialise_test.py
monaco_2018_report/venv/Lib/site-packages/colorama/tests/isatty_test.py
monaco_2018_report/venv/Lib/site-packages/colorama/tests/utils.py
monaco_2018_report/venv/Lib/site-packages/colorama/tests/winterm_test.py
monaco_2018_report-0.0.1.dist-info/LICENSE
monaco_2018_report-0.0.1.dist-info/METADATA
monaco_2018_report-0.0.1.dist-info/WHEEL
monaco_2018_report-0.0.1.dist-info/top_level.txt
monaco_2018_report-0.0.1.dist-info/RECORD
