Metadata-Version: 2.2
Name: monaco_2018_report
Version: 0.0.1
Summary: Processes racing data to generate a detailed report of racer statistics.
Author-email: Suelen Karbivnychyy <suelenkarb@gmail.com>
Classifier: Programming Language :: Python :: 3
Classifier: License :: OSI Approved :: MIT License
Classifier: Operating System :: OS Independent
Requires-Python: >=3.8
License-File: LICENSE
